deeprepo/__init__.py
deeprepo/client.py
deeprepo/ingestion.py
deeprepo/interfaces.py
deeprepo/registry.py
deeprepo/storage.py
deeprepo/mcp/__init__.py
deeprepo/mcp/server.py
deeprepo/providers/__init__.py
deeprepo/providers/anthropic_v.py
deeprepo/providers/gemini_v.py
deeprepo/providers/huggingface_v.py
deeprepo/providers/ollama_v.py
deeprepo/providers/openai_v.py
deeprepo-1.0.0.dist-info/licenses/LICENSE
deeprepo-1.0.0.dist-info/METADATA
deeprepo-1.0.0.dist-info/WHEEL
deeprepo-1.0.0.dist-info/entry_points.txt
deeprepo-1.0.0.dist-info/top_level.txt
deeprepo-1.0.0.dist-info/RECORD
